figures_super_mega_project/__init__.py
figures_super_mega_project/main.py
figures_super_mega_project-0.0.2.dist-info/METADATA
figures_super_mega_project-0.0.2.dist-info/WHEEL
figures_super_mega_project-0.0.2.dist-info/licenses/LICENSE.txt
figures_super_mega_project-0.0.2.dist-info/RECORD
