Metadata-Version: 2.4
Name: figures_super_mega_project
Version: 0.0.2
Summary: Библиотека создана для отправки отклика на hh.ru
Author: Ilya Mikhailov
License-File: LICENSE.txt
Classifier: License :: OSI Approved :: MIT License
Classifier: Operating System :: OS Independent
Classifier: Programming Language :: Python :: 3
